spikesafe_python/ChannelData.py
spikesafe_python/Compensation.py
spikesafe_python/DigitizerData.py
spikesafe_python/DigitizerDataFetch.py
spikesafe_python/DigitizerEnums.py
spikesafe_python/DigitizerInfo.py
spikesafe_python/DigitizerVfCustomSequence.py
spikesafe_python/DigitizerVfCustomSequenceStep.py
spikesafe_python/Discharge.py
spikesafe_python/EventData.py
spikesafe_python/MemoryTableReadData.py
spikesafe_python/Precision.py
spikesafe_python/PulseWidthCorrection.py
spikesafe_python/ReadAllEvents.py
spikesafe_python/ScpiFormatter.py
spikesafe_python/SerialPortConnection.py
spikesafe_python/SpikeSafeEnums.py
spikesafe_python/SpikeSafeError.py
spikesafe_python/SpikeSafeEvents.py
spikesafe_python/SpikeSafeInfo.py
spikesafe_python/SpikeSafeInfoParser.py
spikesafe_python/TcpSocket.py
spikesafe_python/TemperatureData.py
spikesafe_python/Threading.py
spikesafe_python/__init__.py
spikesafe_python-1.11.22.dist-info/licenses/LICENSE
spikesafe_python-1.11.22.dist-info/METADATA
spikesafe_python-1.11.22.dist-info/WHEEL
spikesafe_python-1.11.22.dist-info/top_level.txt
spikesafe_python-1.11.22.dist-info/RECORD
