Metadata-Version: 2.4
Name: spikesafe-python
Version: 1.11.22
Summary: SpikeSafe Python Library
Author-email: Vektrex <support@vektrex.com>
Classifier: Programming Language :: Python :: 3
Classifier: Programming Language :: Python :: 3.10
Classifier: Programming Language :: Python :: 3.11
Classifier: Programming Language :: Python :: 3.12
Classifier: Programming Language :: Python :: 3.13
Classifier: Programming Language :: Python :: 3.14
Classifier: License :: OSI Approved :: MIT License
Classifier: Operating System :: OS Independent
Requires-Python: >=3.10
License-File: LICENSE
Requires-Dist: jsonschema>=4.2.3
Requires-Dist: pyserial>=3.5
Dynamic: license-file
